MANIFEST.in
README.md
setup.py
pipeloyus/__init__.py
pipeloyus/eloyus.py
pipeloyus.egg-info/PKG-INFO
pipeloyus.egg-info/SOURCES.txt
pipeloyus.egg-info/dependency_links.txt
pipeloyus.egg-info/top_level.txt